PDBViewer/PDBViewer.py
PDBViewer/__init__.py
PDBViewer-0.1.2.dist-info/LICENSE.txt
PDBViewer-0.1.2.dist-info/METADATA
PDBViewer-0.1.2.dist-info/WHEEL
PDBViewer-0.1.2.dist-info/top_level.txt
PDBViewer-0.1.2.dist-info/RECORD
